zhijian/__init__.py
zhijian/data/__init__.py
zhijian/data/aid.py
zhijian/data/aircraft.py
zhijian/data/base.py
zhijian/data/caltech101.py
zhijian/data/cars.py
zhijian/data/config.py
zhijian/data/cub2011.py
zhijian/data/dogs.py
zhijian/data/domain.py
zhijian/data/domainnet.py
zhijian/data/dtd.py
zhijian/data/eurosat.py
zhijian/data/flowers.py
zhijian/data/nabirds.py
zhijian/data/officehome.py
zhijian/data/oxford_iiit_pet.py
zhijian/data/pacs.py
zhijian/data/pcam.py
zhijian/data/resisc45.py
zhijian/data/smallnorb.py
zhijian/data/sun397.py
zhijian/data/template.py
zhijian/models/__init__.py
zhijian/models/utils.py
zhijian/models/addin/__init__.py
zhijian/models/addin/base.py
zhijian/models/addin/module/__init__.py
zhijian/models/addin/module/adapter.py
zhijian/models/addin/module/adaptformer.py
zhijian/models/addin/module/base.py
zhijian/models/addin/module/convpass.py
zhijian/models/addin/module/fact_tk.py
zhijian/models/addin/module/fact_tt.py
zhijian/models/addin/module/lora.py
zhijian/models/addin/module/partial_k.py
zhijian/models/addin/module/ssf.py
zhijian/models/addin/module/vpt.py
zhijian/models/addin/module/vqt.py
zhijian/models/backbone/__init__.py
zhijian/models/backbone/base.py
zhijian/models/backbone/customized.py
zhijian/models/backbone/wrapper.py
zhijian/models/backbone/clip/__init__.py
zhijian/models/backbone/clip/utils.py
zhijian/models/backbone/timm/__init__.py
zhijian/models/backbone/timm/arguments.py
zhijian/models/backbone/timm/hooks.py
zhijian/models/configs/__init__.py
zhijian/models/configs/base.py
zhijian/models/kd/__init__.py
zhijian/models/kd/base.py
zhijian/models/kd/loss/__init__.py
zhijian/models/kd/loss/ab.py
zhijian/models/kd/loss/afd.py
zhijian/models/kd/loss/at.py
zhijian/models/kd/loss/bss.py
zhijian/models/kd/loss/cc.py
zhijian/models/kd/loss/crd.py
zhijian/models/kd/loss/customized.py
zhijian/models/kd/loss/dml.py
zhijian/models/kd/loss/fitnet.py
zhijian/models/kd/loss/fsp.py
zhijian/models/kd/loss/ft.py
zhijian-0.0.3.dist-info/LICENSE
zhijian-0.0.3.dist-info/METADATA
zhijian-0.0.3.dist-info/WHEEL
zhijian-0.0.3.dist-info/top_level.txt
zhijian-0.0.3.dist-info/RECORD
